pyhockey/__init__.py
pyhockey/goalie_games.py
pyhockey/goalie_seasons.py
pyhockey/skater_games.py
pyhockey/skater_seasons.py
pyhockey/team_games.py
pyhockey/team_seasons.py
pyhockey/util/config.py
pyhockey/util/data_disclaimer.py
pyhockey/util/db_connect.py
pyhockey/util/input_validation.py
pyhockey/util/query_builder.py
pyhockey/util/query_table.py
pyhockey-0.2.0.dist-info/licenses/LICENSE
pyhockey-0.2.0.dist-info/METADATA
pyhockey-0.2.0.dist-info/WHEEL
pyhockey-0.2.0.dist-info/top_level.txt
pyhockey-0.2.0.dist-info/RECORD
