Metadata-Version: 2.4
Name: pyhockey
Version: 0.2.0
Summary: Library for easy querying of advanced NHL statistics.
Author-email: Sohraub Pazuki <sohraubpazuki@gmail.com>
License-Expression: GPL-2.0-or-later
Keywords: hockey,stats,statistics,NHL,data
Requires-Python: >=3.12
License-File: LICENSE
Requires-Dist: duckdb==1.3.2
Requires-Dist: polars>=1.29.0
Requires-Dist: pytest>=8.4.2
Requires-Dist: pyarrow>=21.0.0
Requires-Dist: numpy<2,>=1.26.0
Requires-Dist: pandas>=2.1.0
Requires-Dist: pdoc>=16.0.0
Dynamic: license-file
